LICENSE
README.md
setup.cfg
setup.py
src/Flask_PyTelegramBotAPI.egg-info/PKG-INFO
src/Flask_PyTelegramBotAPI.egg-info/SOURCES.txt
src/Flask_PyTelegramBotAPI.egg-info/dependency_links.txt
src/Flask_PyTelegramBotAPI.egg-info/requires.txt
src/Flask_PyTelegramBotAPI.egg-info/top_level.txt
src/flask_pytelegrambotapi/__init__.py
src/flask_pytelegrambotapi/extension.py
src/flask_pytelegrambotapi/mixins.py
src/flask_pytelegrambotapi/utils.py