Metadata-Version: 2.1
Name: Flask-PyTelegramBotAPI
Version: 0.0.5
Summary: Интеграция Flask c PyTelegramBotAPI
Home-page: https://github.com/kuzmichus/flask-pytelegrambotapi
Author: kuzmichus
License-File: LICENSE
